MANIFEST.in
README
setup.py
django_echelon.egg-info/PKG-INFO
django_echelon.egg-info/SOURCES.txt
django_echelon.egg-info/dependency_links.txt
django_echelon.egg-info/top_level.txt
echelon/__init__.py
echelon/fields.py
echelon/middleware.py
echelon/models.py
echelon/tests.py
echelon/urls.py
echelon/views.py
echelon/templatetags/__init__.py
echelon/templatetags/echelon_changelog.py
example/__init__.py
example/manage.py
example/settings.py
example/urls.py