Metadata-Version: 1.1
Name: django-echelon
Version: 1.2
Summary: Middleware to make user information always available and to automatically log changes
Home-page: http://github.com/seveas/django-echelon
Author: Dennis Kaarsemaker
Author-email: dennis@kaarsemaker.net
License: UNKNOWN
Platform: UNKNOWN
Classifier: Framework :: Django
Classifier: Intended Audience :: Developers
Classifier: Operating System :: OS Independent
Classifier: Topic :: Software Development
